{
  "instituicoes": [
    {
      "id": 1,
      "nome": "PUC MG",
      "cnpj": "121213",
      "telefone": "34324324",
      "email": "caminhasian@gmail.com",
      "responsavel": "Zezé Perrela",
      "descricao": "TI",
      "conta": "1212",
      "agencia": "334",
      "senha": "123",
      "idEndereco": 1,
      "cursos": [
        1
      ]
    },
    {
      "id": 2,
      "nome": "Casa Caminhas",
      "cnpj": "234343423434234",
      "telefone": "343432",
      "email": "casa@gmail.com",
      "responsavel": "Zezé Perrela",
      "descricao": "sdfsdf",
      "conta": "132133",
      "agencia": "34534d435",
      "senha": "123",
      "idEndereco": 7,
      "cursos": [
        2
      ]
    }
  ]
}
